rm_synthesis-0.1.1.data/scripts/rmsynthesis
rmsynthesis/rmsynthesis.py
rmsynthesis/__init__.py
rm_synthesis-0.1.1.dist-info/RECORD
rm_synthesis-0.1.1.dist-info/METADATA
rm_synthesis-0.1.1.dist-info/WHEEL
rm_synthesis-0.1.1.dist-info/top_level.txt
rm_synthesis-0.1.1.dist-info/DESCRIPTION.rst
rm_synthesis-0.1.1.dist-info/metadata.json
